apimaticcli/__init__.py
apimaticcli/__main__.py
apimaticcli/api_transformer.py
apimaticcli/api_validator.py
apimaticcli/argument_adder.py
apimaticcli/argument_parser.py
apimaticcli/http_response_catcher.py
apimaticcli/sdk_generator.py
apimaticcli/utilities.py
apimaticcli/apimatic/__init__.py
apimaticcli/apimatic/api_helper.py
apimaticcli/apimatic/apimatic_client.py
apimaticcli/apimatic/configuration.py
apimaticcli/apimatic/decorators.py
apimaticcli/apimatic/controllers/__init__.py
apimaticcli/apimatic/controllers/base_controller.py
apimaticcli/apimatic/controllers/generator_controller.py
apimaticcli/apimatic/controllers/transformer_controller.py
apimaticcli/apimatic/controllers/validator_controller.py
apimaticcli/apimatic/exceptions/__init__.py
apimaticcli/apimatic/exceptions/api_exception.py
apimaticcli/apimatic/http/__init__.py
apimaticcli/apimatic/http/http_call_back.py
apimaticcli/apimatic/http/http_client.py
apimaticcli/apimatic/http/http_context.py
apimaticcli/apimatic/http/http_method_enum.py
apimaticcli/apimatic/http/http_request.py
apimaticcli/apimatic/http/http_response.py
apimaticcli/apimatic/http/requests_client.py
apimaticcli/apimatic/http/auth/__init__.py
apimaticcli/apimatic/http/auth/custom_header_auth.py
apimaticcli/apimatic/models/__init__.py
apimaticcli/apimatic/models/validation_summary.py
apimatic_cli-2.5.dist-info/LICENSE
apimatic_cli-2.5.dist-info/METADATA
apimatic_cli-2.5.dist-info/WHEEL
apimatic_cli-2.5.dist-info/entry_points.txt
apimatic_cli-2.5.dist-info/top_level.txt
apimatic_cli-2.5.dist-info/RECORD
