Metadata-Version: 2.1
Name: apimatic-cli
Version: 2.5
Summary: A command line interface for APIMatic.
Home-page: https://apimatic.io/
Author: Shahid Khaliq
Author-email: shahid.khaliq@apimatic.io
License: UNKNOWN
Platform: UNKNOWN
Requires-Dist: requests (<3.0,>=2.9.1)
Requires-Dist: jsonpickle (<1.0,>=0.7.1)
Requires-Dist: cachecontrol (<1.0,>=0.11.7)
Requires-Dist: python-dateutil (<3.0,>=2.5.3)
